LICENSE
README.md
setup.py
algo_fun/__init__.py
algo_fun/add.py
algo_fun_add.egg-info/PKG-INFO
algo_fun_add.egg-info/SOURCES.txt
algo_fun_add.egg-info/dependency_links.txt
algo_fun_add.egg-info/top_level.txt
tests/__init__.py
tests/test_add.py