Metadata-Version: 2.1
Name: algo-fun-add
Version: 0.2.0
Summary: Simple script to add numbers together
Home-page: https://gitlab.com/ChristopheLagaillarde/add_algo
Author: Christophe Lagaillarde
Author-email: chrislag94@gmail.com
License: MIT
License-File: LICENSE
